[{"ask": {"raw": "12.95", "fmt": "12.95", "sort": 12.95}, "bid": {"raw": "12.85", "fmt": "12.85", "sort": 12.85}, "change": "0.25", "changePercent": "1.97%", "changeStatus": "up", "exchange": "TAI", "holdingType": "EQUITY", "limitDown": false, "limitDownPrice": {"raw": "11.45", "fmt": "11.45", "sort": 11.45}, "limitUp": false, "limitUpPrice": {"raw": "13.95", "fmt": "13.95", "sort": 13.95}, "marketStatus": "close", "openInterest": null, "messageBoardId": "finmb_11500443_lang_zh", "optionType": null, "previousVolume": "1008000", "price": "12.95", "priceDiff": null, "regularMarketDayHigh": "13.05", "regularMarketDayLow": "12.8", "regularMarketOpen": "12.8", "regularMarketPreviousClose": "12.7", "regularMarketTime": "2026-06-12T05:30:00Z", "relatedSymbol": null, "relatedSymbolName": null, "sectorId": "42", "sectorName": "\u5149\u96fb", "strikePrice": null, "symbol": "3050.TW", "symbolName": "\u923a\u5fb7", "systexId": "3050", "turnoverM": "12.34", "volume": "956000", "currency": "TWD", "epsTrailingTwelveMonths": null, "exchangeDataDelayedBy": 0, "fiftyTwoWeekHigh": null, "fiftyTwoWeekLow": null, "marketCap": null, "marketState": null, "trailingPE": null, "avgPrice": "12.91", "inMarket": 371, "outMarket": 505, "orderbook": [{"ask": "12.95", "askVol": 11000, "bid": "12.85", "bidVol": 11000, "askVolK": 11, "bidVolK": 11}, {"ask": "13.00", "askVol": 76000, "bid": "12.80", "bidVol": 51000, "askVolK": 76, "bidVolK": 51}, {"ask": "13.05", "askVol": 44000, "bid": "12.75", "bidVol": 27000, "askVolK": 44, "bidVolK": 27}, {"ask": "13.10", "askVol": 48000, "bid": "12.70", "bidVol": 32000, "askVolK": 48, "bidVolK": 32}, {"ask": "13.15", "askVol": 42000, "bid": "12.65", "bidVol": 156000, "askVolK": 42, "bidVolK": 156}], "indexMeta": null, "singleVolume": "111000", "singleVolumeK": "111", "previousVolumeK": 1008, "volumeK": 956, "totalMarketVolK": 876, "inMarketPercentage": "42.35%", "outMarketPercentage": "57.65%", "sumAskVolK": 221, "sumBidVolK": 277}]