[{"ask": {"raw": "46.95", "fmt": "46.95", "sort": 46.95}, "bid": {"raw": "46.65", "fmt": "46.65", "sort": 46.65}, "change": "0.7", "changePercent": "1.52%", "changeStatus": "up", "exchange": "TWO", "holdingType": "EQUITY", "limitDown": false, "limitDownPrice": {"raw": "41.4", "fmt": "41.40", "sort": 41.4}, "limitUp": false, "limitUpPrice": {"raw": "50.5", "fmt": "50.5", "sort": 50.5}, "marketStatus": "close", "openInterest": null, "messageBoardId": "finmb_9755102_lang_zh", "optionType": null, "previousVolume": "1737000", "price": "46.65", "priceDiff": null, "regularMarketDayHigh": "48.75", "regularMarketDayLow": "45.05", "regularMarketOpen": "45.6", "regularMarketPreviousClose": "45.95", "regularMarketTime": "2026-07-02T05:30:00Z", "relatedSymbol": null, "relatedSymbolName": null, "sectorId": "155", "sectorName": "\u6ac3\u5149\u96fb", "strikePrice": null, "symbol": "6234.TWO", "symbolName": "\u9ad8\u50d1", "systexId": "6234", "turnoverM": "45.27", "volume": "960000", "currency": "TWD", "epsTrailingTwelveMonths": null, "exchangeDataDelayedBy": 0, "fiftyTwoWeekHigh": null, "fiftyTwoWeekLow": null, "marketCap": null, "marketState": null, "trailingPE": null, "avgPrice": "47.15", "inMarket": 464, "outMarket": 496, "orderbook": [{"ask": "46.95", "askVol": 1000, "bid": "46.65", "bidVol": 3000, "askVolK": 1, "bidVolK": 3}, {"ask": "47.00", "askVol": 8000, "bid": "46.60", "bidVol": 8000, "askVolK": 8, "bidVolK": 8}, {"ask": "47.10", "askVol": 3000, "bid": "46.55", "bidVol": 9000, "askVolK": 3, "bidVolK": 9}, {"ask": "47.30", "askVol": 1000, "bid": "46.50", "bidVol": 6000, "askVolK": 1, "bidVolK": 6}, {"ask": "47.35", "askVol": 1000, "bid": "46.45", "bidVol": 2000, "askVolK": 1, "bidVolK": 2}], "indexMeta": null, "singleVolume": "39000", "singleVolumeK": "39", "previousVolumeK": 1737, "volumeK": 960, "totalMarketVolK": 960, "inMarketPercentage": "48.33%", "outMarketPercentage": "51.67%", "sumAskVolK": 14, "sumBidVolK": 28}]