[{"ask": {"raw": "8.5", "fmt": "8.50", "sort": 8.5}, "bid": {"raw": "8.49", "fmt": "8.49", "sort": 8.49}, "change": "0.25", "changePercent": "3.03%", "changeStatus": "up", "exchange": "TAI", "holdingType": "EQUITY", "limitDown": false, "limitDownPrice": {"raw": "7.43", "fmt": "7.43", "sort": 7.43}, "limitUp": false, "limitUpPrice": {"raw": "9.07", "fmt": "9.07", "sort": 9.07}, "marketStatus": "close", "openInterest": null, "messageBoardId": "finmb_1054516_lang_zh", "optionType": null, "previousVolume": "32134000", "price": "8.5", "priceDiff": null, "regularMarketDayHigh": "8.52", "regularMarketDayLow": "8.31", "regularMarketOpen": "8.36", "regularMarketPreviousClose": "8.25", "regularMarketTime": "2026-07-02T05:30:00Z", "relatedSymbol": null, "relatedSymbolName": null, "sectorId": "22", "sectorName": "\u91d1\u878d\u696d", "strikePrice": null, "symbol": "2867.TW", "symbolName": "\u4e09\u5546\u58fd", "systexId": "2867", "turnoverM": "97.3", "volume": "11522000", "currency": "TWD", "epsTrailingTwelveMonths": null, "exchangeDataDelayedBy": 0, "fiftyTwoWeekHigh": null, "fiftyTwoWeekLow": null, "marketCap": null, "marketState": null, "trailingPE": null, "avgPrice": "8.44", "inMarket": 3063, "outMarket": 8282, "orderbook": [{"ask": "8.50", "askVol": 33000, "bid": "8.49", "bidVol": 1195000, "askVolK": 33, "bidVolK": 1195}, {"ask": "8.51", "askVol": 63000, "bid": "8.48", "bidVol": 10000, "askVolK": 63, "bidVolK": 10}, {"ask": "8.52", "askVol": 154000, "bid": "8.47", "bidVol": 29000, "askVolK": 154, "bidVolK": 29}, {"ask": "8.53", "askVol": 134000, "bid": "8.46", "bidVol": 41000, "askVolK": 134, "bidVolK": 41}, {"ask": "8.54", "askVol": 341000, "bid": "8.45", "bidVol": 13000, "askVolK": 341, "bidVolK": 13}], "indexMeta": null, "singleVolume": "1112000", "singleVolumeK": "1112", "previousVolumeK": 32134, "volumeK": 11522, "totalMarketVolK": 11345, "inMarketPercentage": "27.00%", "outMarketPercentage": "73.00%", "sumAskVolK": 725, "sumBidVolK": 1288}]