[{"ask": {"raw": "54.8", "fmt": "54.8", "sort": 54.8}, "bid": {"raw": "54.7", "fmt": "54.7", "sort": 54.7}, "change": "0", "changePercent": "0.00%", "changeStatus": "equal", "exchange": "TAI", "holdingType": "EQUITY", "limitDown": false, "limitDownPrice": {"raw": "49.25", "fmt": "49.25", "sort": 49.25}, "limitUp": false, "limitUpPrice": {"raw": "60.1", "fmt": "60.1", "sort": 60.1}, "marketStatus": "close", "openInterest": null, "messageBoardId": "finmb_11149950_lang_zh", "optionType": null, "previousVolume": "3360000", "price": "54.7", "priceDiff": null, "regularMarketDayHigh": "55", "regularMarketDayLow": "54.6", "regularMarketOpen": "54.7", "regularMarketPreviousClose": "54.7", "regularMarketTime": "2026-06-22T05:30:00Z", "relatedSymbol": null, "relatedSymbolName": null, "sectorId": "2", "sectorName": "\u98df\u54c1", "strikePrice": null, "symbol": "1210.TW", "symbolName": "\u5927\u6210", "systexId": "1210", "turnoverM": "87.71", "volume": "1600000", "currency": "TWD", "epsTrailingTwelveMonths": null, "exchangeDataDelayedBy": 0, "fiftyTwoWeekHigh": null, "fiftyTwoWeekLow": null, "marketCap": null, "marketState": null, "trailingPE": null, "avgPrice": "54.8", "inMarket": 954, "outMarket": 646, "orderbook": [{"ask": "54.8", "askVol": 28000, "bid": "54.7", "bidVol": 102000, "askVolK": 28, "bidVolK": 102}, {"ask": "54.9", "askVol": 7000, "bid": "54.6", "bidVol": 117000, "askVolK": 7, "bidVolK": 117}, {"ask": "55.0", "askVol": 128000, "bid": "54.5", "bidVol": 167000, "askVolK": 128, "bidVolK": 167}, {"ask": "55.1", "askVol": 18000, "bid": "54.4", "bidVol": 104000, "askVolK": 18, "bidVolK": 104}, {"ask": "55.2", "askVol": 94000, "bid": "54.3", "bidVol": 112000, "askVolK": 94, "bidVolK": 112}], "indexMeta": null, "singleVolume": "162000", "singleVolumeK": "162", "previousVolumeK": 3360, "volumeK": 1600, "totalMarketVolK": 1600, "inMarketPercentage": "59.62%", "outMarketPercentage": "40.38%", "sumAskVolK": 275, "sumBidVolK": 602}]