[{"ask": {"raw": "101", "fmt": "101.0", "sort": 101}, "bid": {"raw": "100.5", "fmt": "100.5", "sort": 100.5}, "change": "1.8", "changePercent": "1.81%", "changeStatus": "up", "exchange": "TWO", "holdingType": "EQUITY", "limitDown": false, "limitDownPrice": {"raw": "89.3", "fmt": "89.3", "sort": 89.3}, "limitUp": false, "limitUpPrice": {"raw": "109", "fmt": "109.0", "sort": 109}, "marketStatus": "close", "openInterest": null, "messageBoardId": "finmb_12718996_lang_zh", "optionType": null, "previousVolume": "184000", "price": "101", "priceDiff": null, "regularMarketDayHigh": "101", "regularMarketDayLow": "98.1", "regularMarketOpen": "98.6", "regularMarketPreviousClose": "99.2", "regularMarketTime": "2026-03-27T05:30:00Z", "relatedSymbol": null, "relatedSymbolName": null, "sectorId": "154", "sectorName": "\u6ac3\u96fb\u8166\u9031\u908a", "strikePrice": null, "symbol": "3213.TWO", "symbolName": "\u8302\u8a0a", "systexId": "3213", "turnoverM": "15.52", "volume": "156000", "currency": "TWD", "epsTrailingTwelveMonths": null, "exchangeDataDelayedBy": 0, "fiftyTwoWeekHigh": null, "fiftyTwoWeekLow": null, "marketCap": null, "marketState": null, "trailingPE": null, "avgPrice": "99.4", "inMarket": 73, "outMarket": 82, "orderbook": [{"ask": "101.0", "askVol": 7000, "bid": "100.5", "bidVol": 3000, "askVolK": 7, "bidVolK": 3}, {"ask": "101.5", "askVol": 13000, "bid": "100.0", "bidVol": 25000, "askVolK": 13, "bidVolK": 25}, {"ask": "102.0", "askVol": 19000, "bid": "99.9", "bidVol": 3000, "askVolK": 19, "bidVolK": 3}, {"ask": "102.5", "askVol": 11000, "bid": "99.8", "bidVol": 7000, "askVolK": 11, "bidVolK": 7}, {"ask": "103.0", "askVol": 4000, "bid": "99.7", "bidVol": 3000, "askVolK": 4, "bidVolK": 3}], "indexMeta": null, "singleVolume": "8000", "singleVolumeK": "8", "previousVolumeK": 184, "volumeK": 156, "totalMarketVolK": 155, "inMarketPercentage": "47.10%", "outMarketPercentage": "52.90%", "sumAskVolK": 54, "sumBidVolK": 41}]