[{"ask": {"raw": "188", "fmt": "188.0", "sort": 188}, "bid": {"raw": "187.5", "fmt": "187.5", "sort": 187.5}, "change": "0.5", "changePercent": "0.27%", "changeStatus": "up", "exchange": "TAI", "holdingType": "EQUITY", "limitDown": false, "limitDownPrice": {"raw": "169", "fmt": "169.0", "sort": 169}, "limitUp": false, "limitUpPrice": {"raw": "206", "fmt": "206.0", "sort": 206}, "marketStatus": "close", "openInterest": null, "messageBoardId": "finmb_4596653_lang_zh", "optionType": null, "previousVolume": "2212000", "price": "188", "priceDiff": null, "regularMarketDayHigh": "189.5", "regularMarketDayLow": "186.5", "regularMarketOpen": "187", "regularMarketPreviousClose": "187.5", "regularMarketTime": "2026-03-19T05:30:00Z", "relatedSymbol": null, "relatedSymbolName": null, "sectorId": "47", "sectorName": "\u5176\u4ed6\u96fb\u5b50", "strikePrice": null, "symbol": "2474.TW", "symbolName": "\u53ef\u6210", "systexId": "2474", "turnoverM": "399.48", "volume": "2123000", "currency": "TWD", "epsTrailingTwelveMonths": null, "exchangeDataDelayedBy": 0, "fiftyTwoWeekHigh": null, "fiftyTwoWeekLow": null, "marketCap": null, "marketState": null, "trailingPE": null, "avgPrice": "188.1", "inMarket": 949, "outMarket": 1119, "orderbook": [{"ask": "188.0", "askVol": 1000, "bid": "187.5", "bidVol": 277000, "askVolK": 1, "bidVolK": 277}, {"ask": "188.5", "askVol": 57000, "bid": "187.0", "bidVol": 228000, "askVolK": 57, "bidVolK": 228}, {"ask": "189.0", "askVol": 38000, "bid": "186.5", "bidVol": 182000, "askVolK": 38, "bidVolK": 182}, {"ask": "189.5", "askVol": 49000, "bid": "186.0", "bidVol": 163000, "askVolK": 49, "bidVolK": 163}, {"ask": "190.0", "askVol": 111000, "bid": "185.5", "bidVol": 111000, "askVolK": 111, "bidVolK": 111}], "indexMeta": null, "singleVolume": "391000", "singleVolumeK": "391", "previousVolumeK": 2212, "volumeK": 2123, "totalMarketVolK": 2068, "inMarketPercentage": "45.89%", "outMarketPercentage": "54.11%", "sumAskVolK": 256, "sumBidVolK": 961}]