[{"ask": {"raw": "-", "fmt": "-", "sort": null}, "bid": {"raw": "7.18", "fmt": "7.18", "sort": 7.18}, "change": "0.65", "changePercent": "9.95%", "changeStatus": "up", "exchange": "TWO", "holdingType": "EQUITY", "limitDown": false, "limitDownPrice": {"raw": "5.88", "fmt": "5.88", "sort": 5.88}, "limitUp": true, "limitUpPrice": {"raw": "7.18", "fmt": "7.18", "sort": 7.18}, "marketStatus": "close", "openInterest": null, "messageBoardId": "finmb_9845923_lang_zh", "optionType": null, "previousVolume": "192000", "price": "7.18", "priceDiff": null, "regularMarketDayHigh": "7.18", "regularMarketDayLow": "6.53", "regularMarketOpen": "6.53", "regularMarketPreviousClose": "6.53", "regularMarketTime": "2026-03-30T05:30:00Z", "relatedSymbol": null, "relatedSymbolName": null, "sectorId": "98", "sectorName": "\u6ac3\u904b\u52d5\u4f11\u9592", "strikePrice": null, "symbol": "8933.TWO", "symbolName": "\u611b\u5730\u96c5", "systexId": "8933", "turnoverM": "10.05", "volume": "1407000", "currency": "TWD", "epsTrailingTwelveMonths": null, "exchangeDataDelayedBy": 0, "fiftyTwoWeekHigh": null, "fiftyTwoWeekLow": null, "marketCap": null, "marketState": null, "trailingPE": null, "avgPrice": "7.14", "inMarket": 19, "outMarket": 1384, "orderbook": [{"ask": "-", "askVol": 0, "bid": "7.18", "bidVol": 969000, "askVolK": 0, "bidVolK": 969}, {"ask": "-", "askVol": 0, "bid": "7.17", "bidVol": 20000, "askVolK": 0, "bidVolK": 20}, {"ask": "-", "askVol": 0, "bid": "7.16", "bidVol": 3000, "askVolK": 0, "bidVolK": 3}, {"ask": "-", "askVol": 0, "bid": "7.15", "bidVol": 20000, "askVolK": 0, "bidVolK": 20}, {"ask": "-", "askVol": 0, "bid": "7.14", "bidVol": 7000, "askVolK": 0, "bidVolK": 7}], "indexMeta": null, "singleVolume": "16000", "singleVolumeK": "16", "previousVolumeK": 192, "volumeK": 1407, "totalMarketVolK": 1403, "inMarketPercentage": "1.35%", "outMarketPercentage": "98.65%", "sumAskVolK": 0, "sumBidVolK": 1019}]