[{"ask": {"raw": "21.35", "fmt": "21.35", "sort": 21.35}, "bid": {"raw": "21.1", "fmt": "21.10", "sort": 21.1}, "change": "0", "changePercent": "0.00%", "changeStatus": "equal", "exchange": "TWO", "holdingType": "EQUITY", "limitDown": false, "limitDownPrice": {"raw": "19.25", "fmt": "19.25", "sort": 19.25}, "limitUp": false, "limitUpPrice": {"raw": "23.45", "fmt": "23.45", "sort": 23.45}, "marketStatus": "close", "openInterest": null, "messageBoardId": "finmb_206226722_lang_zh", "optionType": null, "previousVolume": "79000", "price": "21.35", "priceDiff": null, "regularMarketDayHigh": "21.5", "regularMarketDayLow": "21.05", "regularMarketOpen": "21.45", "regularMarketPreviousClose": "21.35", "regularMarketTime": "2026-05-04T05:30:00Z", "relatedSymbol": null, "relatedSymbolName": null, "sectorId": "97", "sectorName": "\u6ac3\u7da0\u80fd\u74b0\u4fdd", "strikePrice": null, "symbol": "8440.TWO", "symbolName": "\u7da0\u96fb", "systexId": "8440", "turnoverM": "2.35", "volume": "111000", "currency": "TWD", "epsTrailingTwelveMonths": null, "exchangeDataDelayedBy": 0, "fiftyTwoWeekHigh": null, "fiftyTwoWeekLow": null, "marketCap": null, "marketState": null, "trailingPE": null, "avgPrice": "21.21", "inMarket": 74, "outMarket": 35, "orderbook": [{"ask": "21.35", "askVol": 5000, "bid": "21.10", "bidVol": 14000, "askVolK": 5, "bidVolK": 14}, {"ask": "21.40", "askVol": 6000, "bid": "21.05", "bidVol": 23000, "askVolK": 6, "bidVolK": 23}, {"ask": "21.50", "askVol": 7000, "bid": "21.00", "bidVol": 38000, "askVolK": 7, "bidVolK": 38}, {"ask": "21.55", "askVol": 1000, "bid": "20.95", "bidVol": 3000, "askVolK": 1, "bidVolK": 3}, {"ask": "21.60", "askVol": 4000, "bid": "20.90", "bidVol": 2000, "askVolK": 4, "bidVolK": 2}], "indexMeta": null, "singleVolume": "11000", "singleVolumeK": "11", "previousVolumeK": 79, "volumeK": 111, "totalMarketVolK": 109, "inMarketPercentage": "67.89%", "outMarketPercentage": "32.11%", "sumAskVolK": 23, "sumBidVolK": 80}]