[{"ask": {"raw": "98.2", "fmt": "98.2", "sort": 98.2}, "bid": {"raw": "98", "fmt": "98.0", "sort": 98}, "change": "0.6", "changePercent": "0.62%", "changeStatus": "up", "exchange": "TAI", "holdingType": "EQUITY", "limitDown": false, "limitDownPrice": {"raw": "87.7", "fmt": "87.7", "sort": 87.7}, "limitUp": false, "limitUpPrice": {"raw": "107", "fmt": "107.0", "sort": 107}, "marketStatus": "close", "openInterest": null, "messageBoardId": "finmb_331029920_lang_zh", "optionType": null, "previousVolume": "181000", "price": "98", "priceDiff": null, "regularMarketDayHigh": "99.9", "regularMarketDayLow": "96.8", "regularMarketOpen": "97.9", "regularMarketPreviousClose": "97.4", "regularMarketTime": "2026-06-01T05:30:00Z", "relatedSymbol": null, "relatedSymbolName": null, "sectorId": "30", "sectorName": "\u5176\u4ed6", "strikePrice": null, "symbol": "6585.TW", "symbolName": "\u9f0e\u57fa", "systexId": "6585", "turnoverM": "18.18", "volume": "185000", "currency": "TWD", "epsTrailingTwelveMonths": null, "exchangeDataDelayedBy": 0, "fiftyTwoWeekHigh": null, "fiftyTwoWeekLow": null, "marketCap": null, "marketState": null, "trailingPE": null, "avgPrice": "98.2", "inMarket": 68, "outMarket": 104, "orderbook": [{"ask": "98.2", "askVol": 1000, "bid": "98.0", "bidVol": 1000, "askVolK": 1, "bidVolK": 1}, {"ask": "98.5", "askVol": 1000, "bid": "97.9", "bidVol": 1000, "askVolK": 1, "bidVolK": 1}, {"ask": "98.7", "askVol": 1000, "bid": "97.8", "bidVol": 2000, "askVolK": 1, "bidVolK": 2}, {"ask": "98.8", "askVol": 1000, "bid": "97.7", "bidVol": 2000, "askVolK": 1, "bidVolK": 2}, {"ask": "99.0", "askVol": 3000, "bid": "97.6", "bidVol": 6000, "askVolK": 3, "bidVolK": 6}], "indexMeta": null, "singleVolume": "12000", "singleVolumeK": "12", "previousVolumeK": 181, "volumeK": 185, "totalMarketVolK": 172, "inMarketPercentage": "39.53%", "outMarketPercentage": "60.47%", "sumAskVolK": 7, "sumBidVolK": 12}]