[{"ask": {"raw": "31.45", "fmt": "31.45", "sort": 31.45}, "bid": {"raw": "31.35", "fmt": "31.35", "sort": 31.35}, "change": "-1.6", "changePercent": "-4.86%", "changeStatus": "down", "exchange": "TWO", "holdingType": "EQUITY", "limitDown": false, "limitDownPrice": {"raw": "29.7", "fmt": "29.70", "sort": 29.7}, "limitUp": false, "limitUpPrice": {"raw": "36.2", "fmt": "36.20", "sort": 36.2}, "marketStatus": "close", "openInterest": null, "messageBoardId": "finmb_21811725_lang_zh", "optionType": null, "previousVolume": "1178000", "price": "31.35", "priceDiff": null, "regularMarketDayHigh": "33.7", "regularMarketDayLow": "31.2", "regularMarketOpen": "33.45", "regularMarketPreviousClose": "32.95", "regularMarketTime": "2026-06-11T06:30:00Z", "relatedSymbol": null, "relatedSymbolName": null, "sectorId": "156", "sectorName": "\u6ac3\u901a\u8a0a\u7db2\u8def", "strikePrice": null, "symbol": "3466.TWO", "symbolName": "\u5fb7\u6649", "systexId": "3466", "turnoverM": "25.36", "volume": "794000", "currency": "TWD", "epsTrailingTwelveMonths": null, "exchangeDataDelayedBy": 0, "fiftyTwoWeekHigh": null, "fiftyTwoWeekLow": null, "marketCap": null, "marketState": null, "trailingPE": null, "avgPrice": "31.94", "inMarket": 620, "outMarket": 158, "orderbook": [{"ask": "31.45", "askVol": 1000, "bid": "31.35", "bidVol": 8000, "askVolK": 1, "bidVolK": 8}, {"ask": "31.50", "askVol": 2000, "bid": "31.30", "bidVol": 5000, "askVolK": 2, "bidVolK": 5}, {"ask": "31.55", "askVol": 7000, "bid": "31.25", "bidVol": 4000, "askVolK": 7, "bidVolK": 4}, {"ask": "31.60", "askVol": 4000, "bid": "31.20", "bidVol": 9000, "askVolK": 4, "bidVolK": 9}, {"ask": "31.70", "askVol": 1000, "bid": "31.15", "bidVol": 5000, "askVolK": 1, "bidVolK": 5}], "indexMeta": null, "singleVolume": "3000", "singleVolumeK": "3", "previousVolumeK": 1178, "volumeK": 794, "totalMarketVolK": 778, "inMarketPercentage": "79.69%", "outMarketPercentage": "20.31%", "sumAskVolK": 15, "sumBidVolK": 31}]