[{"ask": {"raw": "206", "fmt": "206.0", "sort": 206}, "bid": {"raw": "205.5", "fmt": "205.5", "sort": 205.5}, "change": "1", "changePercent": "0.49%", "changeStatus": "up", "exchange": "TAI", "holdingType": "EQUITY", "limitDown": false, "limitDownPrice": {"raw": "184.5", "fmt": "184.5", "sort": 184.5}, "limitUp": false, "limitUpPrice": {"raw": "225.5", "fmt": "225.5", "sort": 225.5}, "marketStatus": "close", "openInterest": null, "messageBoardId": "finmb_20297001_lang_zh", "optionType": null, "previousVolume": "238000", "price": "206", "priceDiff": null, "regularMarketDayHigh": "206.5", "regularMarketDayLow": "205", "regularMarketOpen": "205.5", "regularMarketPreviousClose": "205", "regularMarketTime": "2026-07-23T05:30:00Z", "relatedSymbol": null, "relatedSymbolName": null, "sectorId": "94", "sectorName": "\u6578\u4f4d\u96f2\u7aef", "strikePrice": null, "symbol": "3130.TW", "symbolName": "\u4e00\u96f6\u56db", "systexId": "3130", "turnoverM": "34.6", "volume": "168000", "currency": "TWD", "epsTrailingTwelveMonths": null, "exchangeDataDelayedBy": 0, "fiftyTwoWeekHigh": null, "fiftyTwoWeekLow": null, "marketCap": null, "marketState": null, "trailingPE": null, "avgPrice": "205.9", "inMarket": 31, "outMarket": 137, "orderbook": [{"ask": "206.0", "askVol": 1000, "bid": "205.5", "bidVol": 2000, "askVolK": 1, "bidVolK": 2}, {"ask": "206.5", "askVol": 1000, "bid": "205.0", "bidVol": 7000, "askVolK": 1, "bidVolK": 7}, {"ask": "207.0", "askVol": 2000, "bid": "204.5", "bidVol": 6000, "askVolK": 2, "bidVolK": 6}, {"ask": "207.5", "askVol": 2000, "bid": "204.0", "bidVol": 3000, "askVolK": 2, "bidVolK": 3}, {"ask": "208.0", "askVol": 13000, "bid": "203.5", "bidVol": 2000, "askVolK": 13, "bidVolK": 2}], "indexMeta": null, "singleVolume": "3000", "singleVolumeK": "3", "previousVolumeK": 238, "volumeK": 168, "totalMarketVolK": 168, "inMarketPercentage": "18.45%", "outMarketPercentage": "81.55%", "sumAskVolK": 19, "sumBidVolK": 20}]