[{"ask": {"raw": "129.5", "fmt": "129.5", "sort": 129.5}, "bid": {"raw": "128.5", "fmt": "128.5", "sort": 128.5}, "change": "1.5", "changePercent": "1.18%", "changeStatus": "up", "exchange": "TWO", "holdingType": "EQUITY", "limitDown": false, "limitDownPrice": {"raw": "115", "fmt": "115.0", "sort": 115}, "limitUp": false, "limitUpPrice": {"raw": "140", "fmt": "140.0", "sort": 140}, "marketStatus": "close", "openInterest": null, "messageBoardId": "finmb_symbol_3430_lang_zh", "optionType": null, "previousVolume": "545000", "price": "129", "priceDiff": null, "regularMarketDayHigh": "131.5", "regularMarketDayLow": "126", "regularMarketOpen": "129", "regularMarketPreviousClose": "127.5", "regularMarketTime": "2026-06-16T06:30:00Z", "relatedSymbol": null, "relatedSymbolName": null, "sectorId": "151", "sectorName": "\u6ac3\u5316\u5b78", "strikePrice": null, "symbol": "3430.TWO", "symbolName": "\u5947\u9226\u79d1", "systexId": "3430", "turnoverM": "79.39", "volume": "617000", "currency": "TWD", "epsTrailingTwelveMonths": null, "exchangeDataDelayedBy": 0, "fiftyTwoWeekHigh": null, "fiftyTwoWeekLow": null, "marketCap": null, "marketState": null, "trailingPE": null, "avgPrice": "128.6", "inMarket": 280, "outMarket": 293, "orderbook": [{"ask": "129.5", "askVol": 1000, "bid": "128.5", "bidVol": 1000, "askVolK": 1, "bidVolK": 1}, {"ask": "130.0", "askVol": 3000, "bid": "128.0", "bidVol": 6000, "askVolK": 3, "bidVolK": 6}, {"ask": "130.5", "askVol": 3000, "bid": "127.5", "bidVol": 11000, "askVolK": 3, "bidVolK": 11}, {"ask": "131.0", "askVol": 12000, "bid": "127.0", "bidVol": 13000, "askVolK": 12, "bidVolK": 13}, {"ask": "131.5", "askVol": 2000, "bid": "126.5", "bidVol": 15000, "askVolK": 2, "bidVolK": 15}], "indexMeta": null, "singleVolume": "2000", "singleVolumeK": "2", "previousVolumeK": 545, "volumeK": 617, "totalMarketVolK": 573, "inMarketPercentage": "48.87%", "outMarketPercentage": "51.13%", "sumAskVolK": 21, "sumBidVolK": 46}]