[{"ask": {"raw": "51.5", "fmt": "51.5", "sort": 51.5}, "bid": {"raw": "51.4", "fmt": "51.4", "sort": 51.4}, "change": "2.85", "changePercent": "5.87%", "changeStatus": "up", "exchange": "TAI", "holdingType": "EQUITY", "limitDown": false, "limitDownPrice": {"raw": "43.7", "fmt": "43.70", "sort": 43.7}, "limitUp": false, "limitUpPrice": {"raw": "53.4", "fmt": "53.4", "sort": 53.4}, "marketStatus": "close", "openInterest": null, "messageBoardId": "finmb_7873451_lang_zh", "optionType": null, "previousVolume": "94368000", "price": "51.4", "priceDiff": null, "regularMarketDayHigh": "51.5", "regularMarketDayLow": "49.8", "regularMarketOpen": "51", "regularMarketPreviousClose": "48.55", "regularMarketTime": "2026-06-15T05:30:00Z", "relatedSymbol": null, "relatedSymbolName": null, "sectorId": "42", "sectorName": "\u5149\u96fb", "strikePrice": null, "symbol": "3481.TW", "symbolName": "\u7fa4\u5275", "systexId": "3481", "turnoverM": "4984.36", "volume": "98232000", "currency": "TWD", "epsTrailingTwelveMonths": null, "exchangeDataDelayedBy": 0, "fiftyTwoWeekHigh": null, "fiftyTwoWeekLow": null, "marketCap": null, "marketState": null, "trailingPE": null, "avgPrice": "50.7", "inMarket": 49200, "outMarket": 43671, "orderbook": [{"ask": "51.5", "askVol": 3525000, "bid": "51.4", "bidVol": 574000, "askVolK": 3525, "bidVolK": 574}, {"ask": "51.6", "askVol": 856000, "bid": "51.3", "bidVol": 350000, "askVolK": 856, "bidVolK": 350}, {"ask": "51.7", "askVol": 373000, "bid": "51.2", "bidVol": 553000, "askVolK": 373, "bidVolK": 553}, {"ask": "51.8", "askVol": 653000, "bid": "51.1", "bidVol": 1331000, "askVolK": 653, "bidVolK": 1331}, {"ask": "51.9", "askVol": 487000, "bid": "51.0", "bidVol": 1832000, "askVolK": 487, "bidVolK": 1832}], "indexMeta": null, "singleVolume": "6175000", "singleVolumeK": "6175", "previousVolumeK": 94368, "volumeK": 98232, "totalMarketVolK": 92871, "inMarketPercentage": "52.98%", "outMarketPercentage": "47.02%", "sumAskVolK": 5894, "sumBidVolK": 4640}]