[{"ask": {"raw": "30.85", "fmt": "30.85", "sort": 30.85}, "bid": {"raw": "29.5", "fmt": "29.50", "sort": 29.5}, "change": "-0.1", "changePercent": "-0.34%", "changeStatus": "down", "exchange": "TWO", "holdingType": "EQUITY", "limitDown": false, "limitDownPrice": {"raw": "26.55", "fmt": "26.55", "sort": 26.55}, "limitUp": false, "limitUpPrice": {"raw": "32.45", "fmt": "32.45", "sort": 32.45}, "marketStatus": "close", "openInterest": null, "messageBoardId": "finmb_9648897_lang_zh", "optionType": null, "previousVolume": "2000", "price": "29.4", "priceDiff": null, "regularMarketDayHigh": "29.4", "regularMarketDayLow": "29.4", "regularMarketOpen": "29.4", "regularMarketPreviousClose": "29.5", "regularMarketTime": "2026-06-16T04:28:26Z", "relatedSymbol": null, "relatedSymbolName": null, "sectorId": "145", "sectorName": "\u6ac3\u5176\u4ed6", "strikePrice": null, "symbol": "8905.TWO", "symbolName": "\u88d5\u570b", "systexId": "8905", "turnoverM": "0.03", "volume": "1000", "currency": "TWD", "epsTrailingTwelveMonths": null, "exchangeDataDelayedBy": 0, "fiftyTwoWeekHigh": null, "fiftyTwoWeekLow": null, "marketCap": null, "marketState": null, "trailingPE": null, "avgPrice": "29.40", "inMarket": 0, "outMarket": 1, "orderbook": [{"ask": "30.85", "askVol": 1000, "bid": "29.50", "bidVol": 1000, "askVolK": 1, "bidVolK": 1}, {"ask": "30.90", "askVol": 2000, "bid": "29.30", "bidVol": 1000, "askVolK": 2, "bidVolK": 1}, {"ask": "30.95", "askVol": 2000, "bid": "29.25", "bidVol": 1000, "askVolK": 2, "bidVolK": 1}, {"ask": "31.45", "askVol": 4000, "bid": "29.15", "bidVol": 2000, "askVolK": 4, "bidVolK": 2}, {"ask": "32.40", "askVol": 1000, "bid": "29.05", "bidVol": 1000, "askVolK": 1, "bidVolK": 1}], "indexMeta": null, "singleVolume": "1000", "singleVolumeK": "1", "previousVolumeK": 2, "volumeK": 1, "totalMarketVolK": 1, "inMarketPercentage": "0.00%", "outMarketPercentage": "100.00%", "sumAskVolK": 10, "sumBidVolK": 6}]