[{"ask": {"raw": "29.9", "fmt": "29.90", "sort": 29.9}, "bid": {"raw": "29.15", "fmt": "29.15", "sort": 29.15}, "change": "0.05", "changePercent": "0.17%", "changeStatus": "up", "exchange": "TWO", "holdingType": "EQUITY", "limitDown": false, "limitDownPrice": {"raw": "26.55", "fmt": "26.55", "sort": 26.55}, "limitUp": false, "limitUpPrice": {"raw": "32.35", "fmt": "32.35", "sort": 32.35}, "marketStatus": "close", "openInterest": null, "messageBoardId": "finmb_536537480_lang_zh", "optionType": null, "previousVolume": "3000", "price": "29.5", "priceDiff": null, "regularMarketDayHigh": "30.5", "regularMarketDayLow": "29.5", "regularMarketOpen": "30.5", "regularMarketPreviousClose": "29.45", "regularMarketTime": "2026-04-24T04:45:12Z", "relatedSymbol": null, "relatedSymbolName": null, "sectorId": "121", "sectorName": "\u6ac3\u751f\u6280", "strikePrice": null, "symbol": "6662.TWO", "symbolName": "\u6a02\u65af\u79d1", "systexId": "6662", "turnoverM": "0.09", "volume": "3000", "currency": "TWD", "epsTrailingTwelveMonths": null, "exchangeDataDelayedBy": 0, "fiftyTwoWeekHigh": null, "fiftyTwoWeekLow": null, "marketCap": null, "marketState": null, "trailingPE": null, "avgPrice": "30.06", "inMarket": 1, "outMarket": 2, "orderbook": [{"ask": "29.90", "askVol": 1000, "bid": "29.15", "bidVol": 1000, "askVolK": 1, "bidVolK": 1}, {"ask": "29.95", "askVol": 1000, "bid": "29.10", "bidVol": 3000, "askVolK": 1, "bidVolK": 3}, {"ask": "30.00", "askVol": 2000, "bid": "29.05", "bidVol": 3000, "askVolK": 2, "bidVolK": 3}, {"ask": "30.10", "askVol": 1000, "bid": "29.00", "bidVol": 2000, "askVolK": 1, "bidVolK": 2}, {"ask": "30.15", "askVol": 1000, "bid": "28.90", "bidVol": 2000, "askVolK": 1, "bidVolK": 2}], "indexMeta": null, "singleVolume": "1000", "singleVolumeK": "1", "previousVolumeK": 3, "volumeK": 3, "totalMarketVolK": 3, "inMarketPercentage": "33.33%", "outMarketPercentage": "66.67%", "sumAskVolK": 6, "sumBidVolK": 11}]