[{"ask": {"raw": "24.3", "fmt": "24.30", "sort": 24.3}, "bid": {"raw": "24.25", "fmt": "24.25", "sort": 24.25}, "change": "-2", "changePercent": "-7.60%", "changeStatus": "down", "exchange": "TWO", "holdingType": "EQUITY", "limitDown": false, "limitDownPrice": {"raw": "23.7", "fmt": "23.70", "sort": 23.7}, "limitUp": false, "limitUpPrice": {"raw": "28.9", "fmt": "28.90", "sort": 28.9}, "marketStatus": "close", "openInterest": null, "messageBoardId": "finmb_38010566_lang_zh", "optionType": null, "previousVolume": "2125000", "price": "24.3", "priceDiff": null, "regularMarketDayHigh": "26.7", "regularMarketDayLow": "24.15", "regularMarketOpen": "26.25", "regularMarketPreviousClose": "26.3", "regularMarketTime": "2026-06-05T06:30:00Z", "relatedSymbol": null, "relatedSymbolName": null, "sectorId": "155", "sectorName": "\u6ac3\u5149\u96fb", "strikePrice": null, "symbol": "4729.TWO", "symbolName": "\u7192\u8302", "systexId": "4729", "turnoverM": "56.63", "volume": "2269000", "currency": "TWD", "epsTrailingTwelveMonths": null, "exchangeDataDelayedBy": 0, "fiftyTwoWeekHigh": null, "fiftyTwoWeekLow": null, "marketCap": null, "marketState": null, "trailingPE": null, "avgPrice": "24.96", "inMarket": 1525, "outMarket": 722, "orderbook": [{"ask": "24.30", "askVol": 24000, "bid": "24.25", "bidVol": 12000, "askVolK": 24, "bidVolK": 12}, {"ask": "24.35", "askVol": 4000, "bid": "24.20", "bidVol": 10000, "askVolK": 4, "bidVolK": 10}, {"ask": "24.45", "askVol": 2000, "bid": "24.15", "bidVol": 15000, "askVolK": 2, "bidVolK": 15}, {"ask": "24.50", "askVol": 4000, "bid": "24.10", "bidVol": 14000, "askVolK": 4, "bidVolK": 14}, {"ask": "24.65", "askVol": 1000, "bid": "24.05", "bidVol": 18000, "askVolK": 1, "bidVolK": 18}], "indexMeta": null, "singleVolume": "1000", "singleVolumeK": "1", "previousVolumeK": 2125, "volumeK": 2269, "totalMarketVolK": 2247, "inMarketPercentage": "67.87%", "outMarketPercentage": "32.13%", "sumAskVolK": 35, "sumBidVolK": 69}]