[{"ask": {"raw": "63.6", "fmt": "63.6", "sort": 63.6}, "bid": {"raw": "63.5", "fmt": "63.5", "sort": 63.5}, "change": "-2.8", "changePercent": "-4.22%", "changeStatus": "down", "exchange": "TAI", "holdingType": "EQUITY", "limitDown": false, "limitDownPrice": {"raw": "59.7", "fmt": "59.7", "sort": 59.7}, "limitUp": false, "limitUpPrice": {"raw": "72.9", "fmt": "72.9", "sort": 72.9}, "marketStatus": "close", "openInterest": null, "messageBoardId": "finmb_9844079_lang_zh", "optionType": null, "previousVolume": "7137000", "price": "63.5", "priceDiff": null, "regularMarketDayHigh": "63.9", "regularMarketDayLow": "59.7", "regularMarketOpen": "59.8", "regularMarketPreviousClose": "66.3", "regularMarketTime": "2026-06-08T05:30:00Z", "relatedSymbol": null, "relatedSymbolName": null, "sectorId": "44", "sectorName": "\u96fb\u5b50\u96f6\u7d44\u4ef6", "strikePrice": null, "symbol": "2402.TW", "symbolName": "\u6bc5\u5609", "systexId": "2402", "turnoverM": "366.15", "volume": "5996000", "currency": "TWD", "epsTrailingTwelveMonths": null, "exchangeDataDelayedBy": 0, "fiftyTwoWeekHigh": null, "fiftyTwoWeekLow": null, "marketCap": null, "marketState": null, "trailingPE": null, "avgPrice": "61.0", "inMarket": 2996, "outMarket": 2491, "orderbook": [{"ask": "63.6", "askVol": 21000, "bid": "63.5", "bidVol": 17000, "askVolK": 21, "bidVolK": 17}, {"ask": "63.7", "askVol": 71000, "bid": "63.4", "bidVol": 12000, "askVolK": 71, "bidVolK": 12}, {"ask": "63.8", "askVol": 10000, "bid": "63.3", "bidVol": 31000, "askVolK": 10, "bidVolK": 31}, {"ask": "63.9", "askVol": 8000, "bid": "63.2", "bidVol": 79000, "askVolK": 8, "bidVolK": 79}, {"ask": "64.0", "askVol": 15000, "bid": "63.1", "bidVol": 18000, "askVolK": 15, "bidVolK": 18}], "indexMeta": null, "singleVolume": "93000", "singleVolumeK": "93", "previousVolumeK": 7137, "volumeK": 5996, "totalMarketVolK": 5487, "inMarketPercentage": "54.60%", "outMarketPercentage": "45.40%", "sumAskVolK": 125, "sumBidVolK": 157}]