[{"ask": {"raw": "6.65", "fmt": "6.65", "sort": 6.65}, "bid": {"raw": "-", "fmt": "-", "sort": null}, "change": "-0.73", "changePercent": "-9.89%", "changeStatus": "down", "exchange": "TAI", "holdingType": "EQUITY", "limitDown": true, "limitDownPrice": {"raw": "6.65", "fmt": "6.65", "sort": 6.65}, "limitUp": false, "limitUpPrice": {"raw": "8.11", "fmt": "8.11", "sort": 8.11}, "marketStatus": "close", "openInterest": null, "messageBoardId": "finmb_59505315_lang_zh", "optionType": null, "previousVolume": "717000", "price": "6.65", "priceDiff": null, "regularMarketDayHigh": "6.65", "regularMarketDayLow": "6.65", "regularMarketOpen": "6.65", "regularMarketPreviousClose": "7.38", "regularMarketTime": "2026-03-09T05:30:00Z", "relatedSymbol": null, "relatedSymbolName": null, "sectorId": "6", "sectorName": "\u96fb\u6a5f\u6a5f\u68b0", "strikePrice": null, "symbol": "1589.TW", "symbolName": "\u6c38\u51a0-KY", "systexId": "1589", "turnoverM": "3.5", "volume": "526000", "currency": "TWD", "epsTrailingTwelveMonths": null, "exchangeDataDelayedBy": 0, "fiftyTwoWeekHigh": null, "fiftyTwoWeekLow": null, "marketCap": null, "marketState": null, "trailingPE": null, "avgPrice": "6.65", "inMarket": 287, "outMarket": 0, "orderbook": [{"ask": "6.65", "askVol": 6914000, "bid": "-", "bidVol": 0, "askVolK": 6914, "bidVolK": 0}, {"ask": "6.66", "askVol": 2000, "bid": "-", "bidVol": 0, "askVolK": 2, "bidVolK": 0}, {"ask": "6.69", "askVol": 3000, "bid": "-", "bidVol": 0, "askVolK": 3, "bidVolK": 0}, {"ask": "6.70", "askVol": 4000, "bid": "-", "bidVol": 0, "askVolK": 4, "bidVolK": 0}, {"ask": "7.00", "askVol": 5000, "bid": "-", "bidVol": 0, "askVolK": 5, "bidVolK": 0}], "indexMeta": null, "singleVolume": "56000", "singleVolumeK": "56", "previousVolumeK": 717, "volumeK": 526, "totalMarketVolK": 287, "inMarketPercentage": "100.00%", "outMarketPercentage": "0.00%", "sumAskVolK": 6928, "sumBidVolK": 0}]