[{"ask": {"raw": "204.5", "fmt": "204.5", "sort": 204.5}, "bid": {"raw": "204", "fmt": "204.0", "sort": 204}, "change": "8.5", "changePercent": "4.35%", "changeStatus": "up", "exchange": "TWO", "holdingType": "EQUITY", "limitDown": false, "limitDownPrice": {"raw": "176", "fmt": "176.0", "sort": 176}, "limitUp": false, "limitUpPrice": {"raw": "215", "fmt": "215.0", "sort": 215}, "marketStatus": "close", "openInterest": null, "messageBoardId": "finmb_7622031_lang_zh", "optionType": null, "previousVolume": "4130000", "price": "204", "priceDiff": null, "regularMarketDayHigh": "206", "regularMarketDayLow": "198", "regularMarketOpen": "202.5", "regularMarketPreviousClose": "195.5", "regularMarketTime": "2026-05-07T06:30:00Z", "relatedSymbol": null, "relatedSymbolName": null, "sectorId": "125", "sectorName": "\u6ac3\u96fb\u6a5f", "strikePrice": null, "symbol": "8027.TWO", "symbolName": "\u9226\u6607", "systexId": "8027", "turnoverM": "689.57", "volume": "3411000", "currency": "TWD", "epsTrailingTwelveMonths": null, "exchangeDataDelayedBy": 0, "fiftyTwoWeekHigh": null, "fiftyTwoWeekLow": null, "marketCap": null, "marketState": null, "trailingPE": null, "avgPrice": "202.1", "inMarket": 1801, "outMarket": 1464, "orderbook": [{"ask": "204.5", "askVol": 33000, "bid": "204.0", "bidVol": 10000, "askVolK": 33, "bidVolK": 10}, {"ask": "205.0", "askVol": 39000, "bid": "203.5", "bidVol": 14000, "askVolK": 39, "bidVolK": 14}, {"ask": "205.5", "askVol": 29000, "bid": "203.0", "bidVol": 17000, "askVolK": 29, "bidVolK": 17}, {"ask": "206.0", "askVol": 91000, "bid": "202.5", "bidVol": 52000, "askVolK": 91, "bidVolK": 52}, {"ask": "206.5", "askVol": 18000, "bid": "202.0", "bidVol": 26000, "askVolK": 18, "bidVolK": 26}], "indexMeta": null, "singleVolume": "8000", "singleVolumeK": "8", "previousVolumeK": 4130, "volumeK": 3411, "totalMarketVolK": 3265, "inMarketPercentage": "55.16%", "outMarketPercentage": "44.84%", "sumAskVolK": 210, "sumBidVolK": 119}]