[{"ask": {"raw": "12.2", "fmt": "12.20", "sort": 12.2}, "bid": {"raw": "12.1", "fmt": "12.10", "sort": 12.1}, "change": "-0.15", "changePercent": "-1.22%", "changeStatus": "down", "exchange": "TWO", "holdingType": "EQUITY", "limitDown": false, "limitDownPrice": {"raw": "11.05", "fmt": "11.05", "sort": 11.05}, "limitUp": false, "limitUpPrice": {"raw": "13.45", "fmt": "13.45", "sort": 13.45}, "marketStatus": "close", "openInterest": null, "messageBoardId": "finmb_9406491_lang_zh", "optionType": null, "previousVolume": "319000", "price": "12.1", "priceDiff": null, "regularMarketDayHigh": "12.35", "regularMarketDayLow": "12.05", "regularMarketOpen": "12.25", "regularMarketPreviousClose": "12.25", "regularMarketTime": "2026-06-25T05:30:00Z", "relatedSymbol": null, "relatedSymbolName": null, "sectorId": "160", "sectorName": "\u6ac3\u5176\u4ed6\u96fb\u5b50", "strikePrice": null, "symbol": "8085.TWO", "symbolName": "\u798f\u83ef", "systexId": "8085", "turnoverM": "3.77", "volume": "310000", "currency": "TWD", "epsTrailingTwelveMonths": null, "exchangeDataDelayedBy": 0, "fiftyTwoWeekHigh": null, "fiftyTwoWeekLow": null, "marketCap": null, "marketState": null, "trailingPE": null, "avgPrice": "12.16", "inMarket": 258, "outMarket": 44, "orderbook": [{"ask": "12.20", "askVol": 3000, "bid": "12.10", "bidVol": 6000, "askVolK": 3, "bidVolK": 6}, {"ask": "12.25", "askVol": 4000, "bid": "12.05", "bidVol": 36000, "askVolK": 4, "bidVolK": 36}, {"ask": "12.35", "askVol": 5000, "bid": "12.00", "bidVol": 129000, "askVolK": 5, "bidVolK": 129}, {"ask": "12.40", "askVol": 1000, "bid": "11.95", "bidVol": 6000, "askVolK": 1, "bidVolK": 6}, {"ask": "12.50", "askVol": 3000, "bid": "11.90", "bidVol": 11000, "askVolK": 3, "bidVolK": 11}], "indexMeta": null, "singleVolume": "15000", "singleVolumeK": "15", "previousVolumeK": 319, "volumeK": 310, "totalMarketVolK": 302, "inMarketPercentage": "85.43%", "outMarketPercentage": "14.57%", "sumAskVolK": 16, "sumBidVolK": 188}]