[{"ask": {"raw": "51.6", "fmt": "51.6", "sort": 51.6}, "bid": {"raw": "51.5", "fmt": "51.5", "sort": 51.5}, "change": "-0.8", "changePercent": "-1.53%", "changeStatus": "down", "exchange": "TAI", "holdingType": "EQUITY", "limitDown": false, "limitDownPrice": {"raw": "47.1", "fmt": "47.10", "sort": 47.1}, "limitUp": false, "limitUpPrice": {"raw": "57.5", "fmt": "57.5", "sort": 57.5}, "marketStatus": "close", "openInterest": null, "messageBoardId": "finmb_12720730_lang_zh", "optionType": null, "previousVolume": "631000", "price": "51.5", "priceDiff": null, "regularMarketDayHigh": "52.2", "regularMarketDayLow": "51.2", "regularMarketOpen": "51.2", "regularMarketPreviousClose": "52.3", "regularMarketTime": "2026-03-23T05:30:00Z", "relatedSymbol": null, "relatedSymbolName": null, "sectorId": "20", "sectorName": "\u822a\u904b", "strikePrice": null, "symbol": "2607.TW", "symbolName": "\u69ae\u904b", "systexId": "2607", "turnoverM": "31.36", "volume": "608000", "currency": "TWD", "epsTrailingTwelveMonths": null, "exchangeDataDelayedBy": 0, "fiftyTwoWeekHigh": null, "fiftyTwoWeekLow": null, "marketCap": null, "marketState": null, "trailingPE": null, "avgPrice": "51.5", "inMarket": 337, "outMarket": 243, "orderbook": [{"ask": "51.6", "askVol": 1000, "bid": "51.5", "bidVol": 32000, "askVolK": 1, "bidVolK": 32}, {"ask": "51.8", "askVol": 1000, "bid": "51.4", "bidVol": 39000, "askVolK": 1, "bidVolK": 39}, {"ask": "51.9", "askVol": 13000, "bid": "51.3", "bidVol": 40000, "askVolK": 13, "bidVolK": 40}, {"ask": "52.0", "askVol": 9000, "bid": "51.2", "bidVol": 25000, "askVolK": 9, "bidVolK": 25}, {"ask": "52.1", "askVol": 27000, "bid": "51.1", "bidVol": 37000, "askVolK": 27, "bidVolK": 37}], "indexMeta": null, "singleVolume": "48000", "singleVolumeK": "48", "previousVolumeK": 631, "volumeK": 608, "totalMarketVolK": 580, "inMarketPercentage": "58.10%", "outMarketPercentage": "41.90%", "sumAskVolK": 51, "sumBidVolK": 173}]