[{"ask": {"raw": "32.3", "fmt": "32.30", "sort": 32.3}, "bid": {"raw": "32.25", "fmt": "32.25", "sort": 32.25}, "change": "0.45", "changePercent": "1.41%", "changeStatus": "up", "exchange": "TAI", "holdingType": "EQUITY", "limitDown": false, "limitDownPrice": {"raw": "28.7", "fmt": "28.70", "sort": 28.7}, "limitUp": false, "limitUpPrice": {"raw": "35", "fmt": "35.00", "sort": 35}, "marketStatus": "close", "openInterest": null, "messageBoardId": "finmb_9829321_lang_zh", "optionType": null, "previousVolume": "232000", "price": "32.3", "priceDiff": null, "regularMarketDayHigh": "32.3", "regularMarketDayLow": "31.75", "regularMarketOpen": "31.9", "regularMarketPreviousClose": "31.85", "regularMarketTime": "2026-06-24T05:30:00Z", "relatedSymbol": null, "relatedSymbolName": null, "sectorId": "38", "sectorName": "\u751f\u6280", "strikePrice": null, "symbol": "1734.TW", "symbolName": "\u674f\u8f1d", "systexId": "1734", "turnoverM": "21.15", "volume": "658000", "currency": "TWD", "epsTrailingTwelveMonths": null, "exchangeDataDelayedBy": 0, "fiftyTwoWeekHigh": null, "fiftyTwoWeekLow": null, "marketCap": null, "marketState": null, "trailingPE": null, "avgPrice": "32.14", "inMarket": 232, "outMarket": 398, "orderbook": [{"ask": "32.30", "askVol": 8000, "bid": "32.25", "bidVol": 5000, "askVolK": 8, "bidVolK": 5}, {"ask": "32.35", "askVol": 37000, "bid": "32.20", "bidVol": 24000, "askVolK": 37, "bidVolK": 24}, {"ask": "32.40", "askVol": 14000, "bid": "32.15", "bidVol": 23000, "askVolK": 14, "bidVolK": 23}, {"ask": "32.45", "askVol": 4000, "bid": "32.10", "bidVol": 26000, "askVolK": 4, "bidVolK": 26}, {"ask": "32.50", "askVol": 12000, "bid": "32.05", "bidVol": 35000, "askVolK": 12, "bidVolK": 35}], "indexMeta": null, "singleVolume": "38000", "singleVolumeK": "38", "previousVolumeK": 232, "volumeK": 658, "totalMarketVolK": 630, "inMarketPercentage": "36.83%", "outMarketPercentage": "63.17%", "sumAskVolK": 75, "sumBidVolK": 113}]