[{"ask": {"raw": "31.6", "fmt": "31.60", "sort": 31.6}, "bid": {"raw": "31.5", "fmt": "31.50", "sort": 31.5}, "change": "-0.2", "changePercent": "-0.63%", "changeStatus": "down", "exchange": "TAI", "holdingType": "EQUITY", "limitDown": false, "limitDownPrice": {"raw": "28.55", "fmt": "28.55", "sort": 28.55}, "limitUp": false, "limitUpPrice": {"raw": "34.85", "fmt": "34.85", "sort": 34.85}, "marketStatus": "close", "openInterest": null, "messageBoardId": "finmb_9754577_lang_zh", "optionType": null, "previousVolume": "214000", "price": "31.5", "priceDiff": null, "regularMarketDayHigh": "32", "regularMarketDayLow": "31.4", "regularMarketOpen": "32", "regularMarketPreviousClose": "31.7", "regularMarketTime": "2026-03-25T05:30:00Z", "relatedSymbol": null, "relatedSymbolName": null, "sectorId": "2", "sectorName": "\u98df\u54c1", "strikePrice": null, "symbol": "1225.TW", "symbolName": "\u798f\u61cb\u6cb9", "systexId": "1225", "turnoverM": "4.11", "volume": "130000", "currency": "TWD", "epsTrailingTwelveMonths": null, "exchangeDataDelayedBy": 0, "fiftyTwoWeekHigh": null, "fiftyTwoWeekLow": null, "marketCap": null, "marketState": null, "trailingPE": null, "avgPrice": "31.58", "inMarket": 106, "outMarket": 23, "orderbook": [{"ask": "31.60", "askVol": 1000, "bid": "31.50", "bidVol": 3000, "askVolK": 1, "bidVolK": 3}, {"ask": "31.65", "askVol": 2000, "bid": "31.45", "bidVol": 4000, "askVolK": 2, "bidVolK": 4}, {"ask": "31.70", "askVol": 3000, "bid": "31.40", "bidVol": 8000, "askVolK": 3, "bidVolK": 8}, {"ask": "31.75", "askVol": 1000, "bid": "31.35", "bidVol": 8000, "askVolK": 1, "bidVolK": 8}, {"ask": "31.80", "askVol": 3000, "bid": "31.25", "bidVol": 1000, "askVolK": 3, "bidVolK": 1}], "indexMeta": null, "singleVolume": "6000", "singleVolumeK": "6", "previousVolumeK": 214, "volumeK": 130, "totalMarketVolK": 129, "inMarketPercentage": "82.17%", "outMarketPercentage": "17.83%", "sumAskVolK": 10, "sumBidVolK": 24}]