[{"ask": {"raw": "40.2", "fmt": "40.20", "sort": 40.2}, "bid": {"raw": "40.1", "fmt": "40.10", "sort": 40.1}, "change": "-0.45", "changePercent": "-1.11%", "changeStatus": "down", "exchange": "TAI", "holdingType": "EQUITY", "limitDown": false, "limitDownPrice": {"raw": "36.5", "fmt": "36.50", "sort": 36.5}, "limitUp": false, "limitUpPrice": {"raw": "44.6", "fmt": "44.60", "sort": 44.6}, "marketStatus": "close", "openInterest": null, "messageBoardId": "finmb_309581933_lang_zh", "optionType": null, "previousVolume": "243000", "price": "40.1", "priceDiff": null, "regularMarketDayHigh": "40.95", "regularMarketDayLow": "39.8", "regularMarketOpen": "40.9", "regularMarketPreviousClose": "40.55", "regularMarketTime": "2026-05-08T05:30:00Z", "relatedSymbol": null, "relatedSymbolName": null, "sectorId": "21", "sectorName": "\u89c0\u5149\u9910\u65c5", "strikePrice": null, "symbol": "2748.TW", "symbolName": "\u96f2\u54c1", "systexId": "2748", "turnoverM": "8.06", "volume": "200000", "currency": "TWD", "epsTrailingTwelveMonths": null, "exchangeDataDelayedBy": 0, "fiftyTwoWeekHigh": null, "fiftyTwoWeekLow": null, "marketCap": null, "marketState": null, "trailingPE": null, "avgPrice": "40.29", "inMarket": 132, "outMarket": 66, "orderbook": [{"ask": "40.20", "askVol": 1000, "bid": "40.10", "bidVol": 2000, "askVolK": 1, "bidVolK": 2}, {"ask": "40.40", "askVol": 5000, "bid": "40.05", "bidVol": 14000, "askVolK": 5, "bidVolK": 14}, {"ask": "40.60", "askVol": 4000, "bid": "40.00", "bidVol": 14000, "askVolK": 4, "bidVolK": 14}, {"ask": "40.65", "askVol": 3000, "bid": "39.95", "bidVol": 3000, "askVolK": 3, "bidVolK": 3}, {"ask": "40.70", "askVol": 5000, "bid": "39.90", "bidVol": 5000, "askVolK": 5, "bidVolK": 5}], "indexMeta": null, "singleVolume": "3000", "singleVolumeK": "3", "previousVolumeK": 243, "volumeK": 200, "totalMarketVolK": 198, "inMarketPercentage": "66.67%", "outMarketPercentage": "33.33%", "sumAskVolK": 18, "sumBidVolK": 38}]