[{"ask": {"raw": "14.2", "fmt": "14.20", "sort": 14.2}, "bid": {"raw": "13.95", "fmt": "13.95", "sort": 13.95}, "change": "-0.45", "changePercent": "-3.07%", "changeStatus": "down", "exchange": "TWO", "holdingType": "EQUITY", "limitDown": false, "limitDownPrice": {"raw": "13.2", "fmt": "13.20", "sort": 13.2}, "limitUp": false, "limitUpPrice": {"raw": "16.1", "fmt": "16.10", "sort": 16.1}, "marketStatus": "close", "openInterest": null, "messageBoardId": "finmb_24083805_lang_zh", "optionType": null, "previousVolume": "27000", "price": "14.2", "priceDiff": null, "regularMarketDayHigh": "14.7", "regularMarketDayLow": "13.9", "regularMarketOpen": "14.7", "regularMarketPreviousClose": "14.65", "regularMarketTime": "2026-07-17T05:33:00Z", "relatedSymbol": null, "relatedSymbolName": null, "sectorId": "156", "sectorName": "\u6ac3\u901a\u8a0a\u7db2\u8def", "strikePrice": null, "symbol": "3499.TWO", "symbolName": "\u74b0\u5929\u79d1", "systexId": "3499", "turnoverM": "1.25", "volume": "88000", "currency": "TWD", "epsTrailingTwelveMonths": null, "exchangeDataDelayedBy": 0, "fiftyTwoWeekHigh": null, "fiftyTwoWeekLow": null, "marketCap": null, "marketState": null, "trailingPE": null, "avgPrice": "14.15", "inMarket": 65, "outMarket": 23, "orderbook": [{"ask": "14.20", "askVol": 6000, "bid": "13.95", "bidVol": 1000, "askVolK": 6, "bidVolK": 1}, {"ask": "14.65", "askVol": 3000, "bid": "13.90", "bidVol": 1000, "askVolK": 3, "bidVolK": 1}, {"ask": "14.70", "askVol": 11000, "bid": "13.80", "bidVol": 3000, "askVolK": 11, "bidVolK": 3}, {"ask": "14.75", "askVol": 2000, "bid": "13.30", "bidVol": 1000, "askVolK": 2, "bidVolK": 1}, {"ask": "14.85", "askVol": 1000, "bid": "13.25", "bidVol": 2000, "askVolK": 1, "bidVolK": 2}], "indexMeta": null, "singleVolume": "4000", "singleVolumeK": "4", "previousVolumeK": 27, "volumeK": 88, "totalMarketVolK": 88, "inMarketPercentage": "73.86%", "outMarketPercentage": "26.14%", "sumAskVolK": 23, "sumBidVolK": 8}]