[{"ask": {"raw": "131.5", "fmt": "131.5", "sort": 131.5}, "bid": {"raw": "131", "fmt": "131.0", "sort": 131}, "change": "1", "changePercent": "0.77%", "changeStatus": "up", "exchange": "TWO", "holdingType": "EQUITY", "limitDown": false, "limitDownPrice": {"raw": "117.5", "fmt": "117.5", "sort": 117.5}, "limitUp": false, "limitUpPrice": {"raw": "143.5", "fmt": "143.5", "sort": 143.5}, "marketStatus": "close", "openInterest": null, "messageBoardId": "finmb_30033779_lang_zh", "optionType": null, "previousVolume": "46000", "price": "131.5", "priceDiff": null, "regularMarketDayHigh": "131.5", "regularMarketDayLow": "130", "regularMarketOpen": "130.5", "regularMarketPreviousClose": "130.5", "regularMarketTime": "2026-03-13T05:30:00Z", "relatedSymbol": null, "relatedSymbolName": null, "sectorId": "125", "sectorName": "\u6ac3\u96fb\u6a5f", "strikePrice": null, "symbol": "1580.TWO", "symbolName": "\u65b0\u9ea5", "systexId": "1580", "turnoverM": "4.58", "volume": "35000", "currency": "TWD", "epsTrailingTwelveMonths": null, "exchangeDataDelayedBy": 0, "fiftyTwoWeekHigh": null, "fiftyTwoWeekLow": null, "marketCap": null, "marketState": null, "trailingPE": null, "avgPrice": "130.8", "inMarket": 8, "outMarket": 27, "orderbook": [{"ask": "131.5", "askVol": 1000, "bid": "131.0", "bidVol": 1000, "askVolK": 1, "bidVolK": 1}, {"ask": "132.0", "askVol": 18000, "bid": "130.5", "bidVol": 9000, "askVolK": 18, "bidVolK": 9}, {"ask": "132.5", "askVol": 2000, "bid": "130.0", "bidVol": 11000, "askVolK": 2, "bidVolK": 11}, {"ask": "133.0", "askVol": 2000, "bid": "129.5", "bidVol": 5000, "askVolK": 2, "bidVolK": 5}, {"ask": "133.5", "askVol": 2000, "bid": "129.0", "bidVol": 20000, "askVolK": 2, "bidVolK": 20}], "indexMeta": null, "singleVolume": "4000", "singleVolumeK": "4", "previousVolumeK": 46, "volumeK": 35, "totalMarketVolK": 35, "inMarketPercentage": "22.86%", "outMarketPercentage": "77.14%", "sumAskVolK": 25, "sumBidVolK": 46}]