[{"ask": {"raw": "70.8", "fmt": "70.8", "sort": 70.8}, "bid": {"raw": "70.3", "fmt": "70.3", "sort": 70.3}, "change": "-0.4", "changePercent": "-0.56%", "changeStatus": "down", "exchange": "TWO", "holdingType": "EQUITY", "limitDown": false, "limitDownPrice": {"raw": "63.8", "fmt": "63.8", "sort": 63.8}, "limitUp": false, "limitUpPrice": {"raw": "77.8", "fmt": "77.8", "sort": 77.8}, "marketStatus": "close", "openInterest": null, "messageBoardId": "finmb_9857256_lang_zh", "optionType": null, "previousVolume": "246000", "price": "70.4", "priceDiff": null, "regularMarketDayHigh": "72.1", "regularMarketDayLow": "70.1", "regularMarketOpen": "71.2", "regularMarketPreviousClose": "70.8", "regularMarketTime": "2026-05-28T05:30:00Z", "relatedSymbol": null, "relatedSymbolName": null, "sectorId": "157", "sectorName": "\u6ac3\u96fb\u5b50\u96f6\u7d44\u4ef6", "strikePrice": null, "symbol": "6203.TWO", "symbolName": "\u6d77\u97fb\u96fb", "systexId": "6203", "turnoverM": "25.14", "volume": "354000", "currency": "TWD", "epsTrailingTwelveMonths": null, "exchangeDataDelayedBy": 0, "fiftyTwoWeekHigh": null, "fiftyTwoWeekLow": null, "marketCap": null, "marketState": null, "trailingPE": null, "avgPrice": "71.0", "inMarket": 214, "outMarket": 138, "orderbook": [{"ask": "70.8", "askVol": 2000, "bid": "70.3", "bidVol": 3000, "askVolK": 2, "bidVolK": 3}, {"ask": "71.0", "askVol": 1000, "bid": "70.2", "bidVol": 6000, "askVolK": 1, "bidVolK": 6}, {"ask": "71.3", "askVol": 6000, "bid": "70.1", "bidVol": 29000, "askVolK": 6, "bidVolK": 29}, {"ask": "71.4", "askVol": 3000, "bid": "70.0", "bidVol": 27000, "askVolK": 3, "bidVolK": 27}, {"ask": "71.5", "askVol": 5000, "bid": "69.9", "bidVol": 14000, "askVolK": 5, "bidVolK": 14}], "indexMeta": null, "singleVolume": "11000", "singleVolumeK": "11", "previousVolumeK": 246, "volumeK": 354, "totalMarketVolK": 352, "inMarketPercentage": "60.80%", "outMarketPercentage": "39.20%", "sumAskVolK": 17, "sumBidVolK": 79}]