[{"ask": {"raw": "4190", "fmt": "4,190", "sort": 4190}, "bid": {"raw": "4170", "fmt": "4,170", "sort": 4170}, "change": "235", "changePercent": "5.94%", "changeStatus": "up", "exchange": "TAI", "holdingType": "EQUITY", "limitDown": false, "limitDownPrice": {"raw": "3560", "fmt": "3,560", "sort": 3560}, "limitUp": false, "limitUpPrice": {"raw": "4350", "fmt": "4,350", "sort": 4350}, "marketStatus": "close", "openInterest": null, "messageBoardId": "finmb_12406859_lang_zh", "optionType": null, "previousVolume": "1638000", "price": "4190", "priceDiff": null, "regularMarketDayHigh": "4245", "regularMarketDayLow": "4015", "regularMarketOpen": "4015", "regularMarketPreviousClose": "3955", "regularMarketTime": "2026-04-28T05:30:00Z", "relatedSymbol": null, "relatedSymbolName": null, "sectorId": "40", "sectorName": "\u534a\u5c0e\u9ad4", "strikePrice": null, "symbol": "3443.TW", "symbolName": "\u5275\u610f", "systexId": "3443", "turnoverM": "2697.09", "volume": "647000", "currency": "TWD", "epsTrailingTwelveMonths": null, "exchangeDataDelayedBy": 0, "fiftyTwoWeekHigh": null, "fiftyTwoWeekLow": null, "marketCap": null, "marketState": null, "trailingPE": null, "avgPrice": "4168", "inMarket": 214, "outMarket": 341, "orderbook": [{"ask": "4190", "askVol": 5000, "bid": "4170", "bidVol": 4000, "askVolK": 5, "bidVolK": 4}, {"ask": "4195", "askVol": 3000, "bid": "4160", "bidVol": 1000, "askVolK": 3, "bidVolK": 1}, {"ask": "4200", "askVol": 30000, "bid": "4155", "bidVol": 1000, "askVolK": 30, "bidVolK": 1}, {"ask": "4205", "askVol": 1000, "bid": "4150", "bidVol": 2000, "askVolK": 1, "bidVolK": 2}, {"ask": "4210", "askVol": 3000, "bid": "4140", "bidVol": 1000, "askVolK": 3, "bidVolK": 1}], "indexMeta": null, "singleVolume": "70000", "singleVolumeK": "70", "previousVolumeK": 1638, "volumeK": 647, "totalMarketVolK": 555, "inMarketPercentage": "38.56%", "outMarketPercentage": "61.44%", "sumAskVolK": 42, "sumBidVolK": 9}]