[{"ask": {"raw": "40.55", "fmt": "40.55", "sort": 40.55}, "bid": {"raw": "40.5", "fmt": "40.50", "sort": 40.5}, "change": "0.95", "changePercent": "2.40%", "changeStatus": "up", "exchange": "TWO", "holdingType": "EQUITY", "limitDown": false, "limitDownPrice": {"raw": "35.6", "fmt": "35.60", "sort": 35.6}, "limitUp": false, "limitUpPrice": {"raw": "43.5", "fmt": "43.50", "sort": 43.5}, "marketStatus": "close", "openInterest": null, "messageBoardId": "finmb_1856096_lang_zh", "optionType": null, "previousVolume": "2940000", "price": "40.5", "priceDiff": null, "regularMarketDayHigh": "40.85", "regularMarketDayLow": "39.35", "regularMarketOpen": "39.55", "regularMarketPreviousClose": "39.55", "regularMarketTime": "2026-04-22T06:30:00Z", "relatedSymbol": null, "relatedSymbolName": null, "sectorId": "121", "sectorName": "\u6ac3\u751f\u6280", "strikePrice": null, "symbol": "4123.TWO", "symbolName": "\u665f\u5fb7", "systexId": "4123", "turnoverM": "125.74", "volume": "3139000", "currency": "TWD", "epsTrailingTwelveMonths": null, "exchangeDataDelayedBy": 0, "fiftyTwoWeekHigh": null, "fiftyTwoWeekLow": null, "marketCap": null, "marketState": null, "trailingPE": null, "avgPrice": "40.06", "inMarket": 1444, "outMarket": 1676, "orderbook": [{"ask": "40.55", "askVol": 10000, "bid": "40.50", "bidVol": 13000, "askVolK": 10, "bidVolK": 13}, {"ask": "40.60", "askVol": 40000, "bid": "40.45", "bidVol": 18000, "askVolK": 40, "bidVolK": 18}, {"ask": "40.65", "askVol": 20000, "bid": "40.40", "bidVol": 30000, "askVolK": 20, "bidVolK": 30}, {"ask": "40.70", "askVol": 84000, "bid": "40.35", "bidVol": 16000, "askVolK": 84, "bidVolK": 16}, {"ask": "40.75", "askVol": 140000, "bid": "40.30", "bidVol": 43000, "askVolK": 140, "bidVolK": 43}], "indexMeta": null, "singleVolume": "5000", "singleVolumeK": "5", "previousVolumeK": 2940, "volumeK": 3139, "totalMarketVolK": 3120, "inMarketPercentage": "46.28%", "outMarketPercentage": "53.72%", "sumAskVolK": 294, "sumBidVolK": 120}]